brunt/__init__.py
brunt/client.py
brunt/const.py
brunt/http.py
brunt/thing.py
brunt/utils.py
brunt-1.2.0.dist-info/AUTHORS.rst
brunt-1.2.0.dist-info/LICENSE
brunt-1.2.0.dist-info/LICENSE.txt
brunt-1.2.0.dist-info/METADATA
brunt-1.2.0.dist-info/WHEEL
brunt-1.2.0.dist-info/top_level.txt
brunt-1.2.0.dist-info/RECORD
