Metadata-Version: 2.1
Name: brunt
Version: 1.2.0
Summary: Unofficial python SDK for Brunt, this package allows you to control your Brunt devices from code.
Home-page: https://github.com/eavanvalkenburg/brunt-api
Author: E.A. van Valkenburg
Author-email: edvan@microsoft.com
License: mit
Project-URL: Documentation, https://pyscaffold.org/
Platform: any
Classifier: Development Status :: 4 - Beta
Classifier: Programming Language :: Python
Provides-Extra: test
License-File: LICENSE
License-File: LICENSE.txt
License-File: AUTHORS.rst
